[
    {
    "location": {
      "name": "Vigo",
      "region": "Pontevedra",
      "country": "España",
      "lat": 53.1,
      "lon": -0.13,
      "tz_id": "Europe",
      "localtime_epoch": 1673620218,
      "localtime": "2024-10-23 14:30"
    },
    "current": {
      "last_updated_epoch": 1673620200,
      "last_updated": "2024-10-23 14:30",
      "temp_c": 12.5,
      "temp_f": 54.5,
      "is_day": 1,
      "condition": {
        "text": "Nublado",
        "icon": "//cdn.weatherapi.com/weather/64x64/day/119.png",
        "code": 1006
      },
      "wind_mph": 15.0,
      "wind_kph": 24.1,
      "wind_degree": 270,
      "wind_dir": "W",
      "pressure_mb": 1008.0,
      "pressure_in": 29.77,
      "precip_mm": 0.0,
      "precip_in": 0.0,
      "humidity": 65,
      "cloud": 75,
      "feelslike_c": 10.0,
      "feelslike_f": 50.0,
      "vis_km": 10.0,
      "vis_miles": 6.0,
      "uv": 2.0,
      "gust_mph": 20.0,
      "gust_kph": 32.2
    }
  }

]